{
  "annotations": { "list": [] },
  "editable": true,
  "fiscalYearStartMonth": 0,
  "graphTooltip": 1,
  "id": null,
  "links": [],
  "liveNow": false,
  "panels": [
    {
      "datasource": { "type": "prometheus", "uid": "${datasource}" },
      "fieldConfig": {
        "defaults": {
          "color": { "mode": "palette-classic" },
          "custom": {
            "axisPlacement": "auto",
            "barAlignment": 0,
            "drawStyle": "line",
            "fillOpacity": 20,
            "gradientMode": "opacity",
            "hideFrom": { "legend": false, "tooltip": false, "viz": false },
            "lineInterpolation": "smooth",
            "lineWidth": 1,
            "pointSize": 5,
            "scaleDistribution": { "type": "linear" },
            "showPoints": "never",
            "spanNulls": false,
            "stacking": { "group": "A", "mode": "normal" },
            "thresholdsStyle": { "mode": "off" }
          },
          "mappings": [],
          "thresholds": {
            "mode": "absolute",
            "steps": [{ "color": "green", "value": null }, { "color": "red", "value": 80 }]
          },
          "unit": "short"
        },
        "overrides": []
      },
      "gridPos": { "h": 9, "w": 24, "x": 0, "y": 0 },
      "id": 1,
      "options": {
        "legend": { "calcs": ["lastNotNull"], "displayMode": "table", "placement": "right", "showLegend": true },
        "tooltip": { "mode": "multi", "sort": "desc" }
      },
      "targets": [
        {
          "datasource": { "type": "prometheus", "uid": "${datasource}" },
          "editorMode": "code",
          "expr": "sum by (status) (scrape_jobs_status)",
          "legendFormat": "{{status}}",
          "range": true,
          "refId": "A"
        }
      ],
      "title": "Scrape job rows by status (gauge, refreshed on /metrics scrape)",
      "type": "timeseries"
    },
    {
      "datasource": { "type": "prometheus", "uid": "${datasource}" },
      "fieldConfig": {
        "defaults": {
          "color": { "mode": "palette-classic" },
          "custom": {
            "axisPlacement": "auto",
            "barAlignment": 0,
            "drawStyle": "line",
            "fillOpacity": 0,
            "gradientMode": "none",
            "hideFrom": { "legend": false, "tooltip": false, "viz": false },
            "lineInterpolation": "linear",
            "lineWidth": 1,
            "pointSize": 5,
            "scaleDistribution": { "type": "linear" },
            "showPoints": "never",
            "spanNulls": false,
            "stacking": { "group": "A", "mode": "none" },
            "thresholdsStyle": { "mode": "off" }
          },
          "mappings": [],
          "thresholds": { "mode": "absolute", "steps": [{ "color": "green", "value": null }] },
          "unit": "ops"
        },
        "overrides": []
      },
      "gridPos": { "h": 8, "w": 12, "x": 0, "y": 9 },
      "id": 2,
      "options": {
        "legend": { "calcs": [], "displayMode": "list", "placement": "bottom", "showLegend": true },
        "tooltip": { "mode": "single", "sort": "none" }
      },
      "targets": [
        {
          "datasource": { "type": "prometheus", "uid": "${datasource}" },
          "editorMode": "code",
          "expr": "sum by (kind) (rate(scrape_jobs_enqueued_total[5m]))",
          "legendFormat": "{{kind}}",
          "range": true,
          "refId": "A"
        }
      ],
      "title": "scrape_jobs_enqueued_total (rate)",
      "type": "timeseries"
    },
    {
      "datasource": { "type": "prometheus", "uid": "${datasource}" },
      "fieldConfig": {
        "defaults": {
          "color": { "mode": "palette-classic" },
          "custom": {
            "axisPlacement": "auto",
            "barAlignment": 0,
            "drawStyle": "line",
            "fillOpacity": 0,
            "gradientMode": "none",
            "hideFrom": { "legend": false, "tooltip": false, "viz": false },
            "lineInterpolation": "linear",
            "lineWidth": 1,
            "pointSize": 5,
            "scaleDistribution": { "type": "linear" },
            "showPoints": "never",
            "spanNulls": false,
            "stacking": { "group": "A", "mode": "none" },
            "thresholdsStyle": { "mode": "off" }
          },
          "mappings": [],
          "thresholds": { "mode": "absolute", "steps": [{ "color": "green", "value": null }] },
          "unit": "ops"
        },
        "overrides": []
      },
      "gridPos": { "h": 8, "w": 12, "x": 12, "y": 9 },
      "id": 3,
      "options": {
        "legend": { "calcs": [], "displayMode": "list", "placement": "bottom", "showLegend": true },
        "tooltip": { "mode": "single", "sort": "none" }
      },
      "targets": [
        {
          "datasource": { "type": "prometheus", "uid": "${datasource}" },
          "editorMode": "code",
          "expr": "sum by (status) (rate(scrape_jobs_completed_total[5m]))",
          "legendFormat": "{{status}}",
          "range": true,
          "refId": "A"
        }
      ],
      "title": "scrape_jobs_completed_total (rate)",
      "type": "timeseries"
    },
    {
      "gridPos": { "h": 5, "w": 24, "x": 0, "y": 17 },
      "id": 4,
      "options": {
        "code": { "language": "plaintext", "showLineNumbers": false, "showMiniMap": false },
        "content": "## BullMQ / queue depth (placeholders)\n\nThe Express backend **does not** export BullMQ Redis metrics on `/metrics` today. If you add a compatible exporter or custom metrics, try expressions such as:\n\n- `bullmq_queue_jobs_waiting{queue=~\"$queue\"}` *(metric name may vary)*\n- `bullmq_queue_jobs_active{queue=~\"$queue\"}`\n- Redis exporter: `redis_key_size_bytes{key=~\"bull:.*\"}` *(example only)*\n\nAdd a **Text** or **Query** variable for `queue` and point this dashboard at the job that scrapes those series.",
        "mode": "markdown"
      },
      "title": "BullMQ — generic notes",
      "type": "text"
    }
  ],
  "refresh": "30s",
  "schemaVersion": 39,
  "style": "dark",
  "tags": ["vahan360", "queue", "scrape-jobs"],
  "templating": {
    "list": [
      {
        "current": {},
        "hide": 0,
        "includeAll": false,
        "label": "Prometheus",
        "multi": false,
        "name": "datasource",
        "options": [],
        "query": "prometheus",
        "refresh": 1,
        "regex": "",
        "skipUrlSync": false,
        "type": "datasource"
      }
    ]
  },
  "time": { "from": "now-6h", "to": "now" },
  "timepicker": {},
  "timezone": "",
  "title": "Vahan360 — queue depth (scrape_jobs_*)",
  "uid": "vahan360-queue-depth",
  "version": 1,
  "weekStart": ""
}
